initpkg/__init__.py
initpkg/cli.py
initpkg/template/README.md
initpkg/template/azure-devops.yaml
initpkg/template/makefile
initpkg/template/model_metadata.json
initpkg/template/requirement_prod.txt
initpkg/template/requirements.txt
initpkg/template/setup.cfg
initpkg/template/setup.py
initpkg/template/docs/Makefile
initpkg/template/docs/conf.py
initpkg/template/docs/getting_started.md
initpkg/template/docs/index.rst
initpkg/template/docs/make.bat
initpkg/template/docs/modules.rst
initpkg/template/docs/template.rst
initpkg/template/mlflow/MLproject
initpkg/template/mlflow/conda_env.yml
initpkg/template/template/__init__.py
initpkg/template/template/main.py
initpkg/template/template/etl/__init__.py
initpkg/template/template/etl/extraction_template.py
initpkg/template/template/etl/ingestion_template.py
initpkg/template/template/etl/integration_template.py
initpkg/template/template/etl/transformation_template.py
initpkg/template/template/model/__init__.py
initpkg/template/template/model/feature_engineering_template.py
initpkg/template/template/model/scoring_template.py
initpkg/template/template/model/training_template.py
initpkg/template/template/model/validation_template.py
initpkg/template/template/monitoring/__init__.py
initpkg/template/template/monitoring/monitoring_template.py
initpkg/template/template/serving/__init__.py
initpkg/template/template/serving/deploy_template.py
initpkg/template/template/visualisation/__init__.py
initpkg/template/template/visualisation/dashboard_template.py
initpkg/template/template/visualisation/visualisation_template.py
initpkg/template/tests/__init__.py
initpkg/template/tests/test_main.py
initpkg-0.2.2.dist-info/LICENSE
initpkg-0.2.2.dist-info/METADATA
initpkg-0.2.2.dist-info/WHEEL
initpkg-0.2.2.dist-info/entry_points.txt
initpkg-0.2.2.dist-info/top_level.txt
initpkg-0.2.2.dist-info/RECORD
