Metadata-Version: 2.1
Name: initpkg
Version: 0.2.2
Summary: python package creator
Home-page: http://github.com/wlongxiang/initpkg
Author: Benjamin Wang
Author-email: wlongxiang1119@gmail.com
License: MIT
Platform: UNKNOWN
